eshwar_pandas/__init__.py
eshwar_pandas/core.py
eshwar_pandas-0.1.0.dist-info/METADATA
eshwar_pandas-0.1.0.dist-info/WHEEL
eshwar_pandas-0.1.0.dist-info/top_level.txt
eshwar_pandas-0.1.0.dist-info/RECORD
